matrix_agents_hub/__init__.py
matrix_agents_hub/setup.py
matrix_agents_hub/agent/__init__.py
matrix_agents_hub-0.1.3.dist-info/METADATA
matrix_agents_hub-0.1.3.dist-info/WHEEL
matrix_agents_hub-0.1.3.dist-info/top_level.txt
matrix_agents_hub-0.1.3.dist-info/RECORD
