Metadata-Version: 2.2
Name: matrix-agents-hub
Version: 0.1.3
Summary: A hub for managing AI agents
Home-page: https://github.com/xray918/matrix
Author: Ray Xie
Author-email: xie.xinfa@gmail.com
Classifier: Development Status :: 3 - Alpha
Classifier: Intended Audience :: Developers
Classifier: License :: OSI Approved :: MIT License
Classifier: Operating System :: OS Independent
Classifier: Programming Language :: Python :: 3
Classifier: Programming Language :: Python :: 3.8
Classifier: Programming Language :: Python :: 3.9
Classifier: Programming Language :: Python :: 3.10
Requires-Python: >=3.8
Requires-Dist: requests>=2.25.0
Requires-Dist: python-dotenv>=0.19.0
Requires-Dist: colorlog>=6.7.0
Dynamic: author
Dynamic: author-email
Dynamic: classifier
Dynamic: description
Dynamic: description-content-type
Dynamic: home-page
Dynamic: requires-dist
Dynamic: requires-python
Dynamic: summary
